Metadata-Version: 1.0
Name: guess-number-game-jenny
Version: 0.1
Summary: Number guessing
Home-page: UNKNOWN
Author: UNKNOWN
Author-email: UNKNOWN
License: UNKNOWN
Platform: UNKNOWN
